toodaloo.py
toodaloo-0.0.4.dist-info/LICENSE
toodaloo-0.0.4.dist-info/METADATA
toodaloo-0.0.4.dist-info/WHEEL
toodaloo-0.0.4.dist-info/top_level.txt
toodaloo-0.0.4.dist-info/RECORD
